{
  "project_info": {
    "project_number": "5700655000",
    "project_id": "briefly-today",
    "storage_bucket": "briefly-today.firebasestorage.app"
  },
  "client": [
    {
      "client_info": {
        "mobilesdk_app_id": "1:5700655000:android:d47ff49ba03b19455cfded",
        "android_client_info": {
          "package_name": "com.geap.brieflytoday"
        }
      },
      "oauth_client": [],
      "api_key": [
        {
          "current_key": "AIzaSyALogbpcqVbYloo8jY66uUDP7fbMpeI4gc"
        }
      ],
      "services": {
        "appinvite_service": {
          "other_platform_oauth_client": []
        }
      }
    },
    {
      "client_info": {
        "mobilesdk_app_id": "1:5700655000:android:0253ea16c6aa52fb5cfded",
        "android_client_info": {
          "package_name": "com.geap1999.brieflytoday"
        }
      },
      "oauth_client": [],
      "api_key": [
        {
          "current_key": "AIzaSyALogbpcqVbYloo8jY66uUDP7fbMpeI4gc"
        }
      ],
      "services": {
        "appinvite_service": {
          "other_platform_oauth_client": []
        }
      }
    }
  ],
  "configuration_version": "1"
}